[
  {
    "accessory": [
      {
        "id": 1,
        "inStock": 100,
        "listedOn": "04/01/2024",
        "image": "images/accessory/accessory-1.jpeg",
        "name": "Vievie Tote Bag",
        "type": "For you",
        "price": 25,
        "discount": null
      },
      {
        "id": 2,
        "inStock": 100,
        "listedOn": "04/01/2024",
        "image": "images/accessory/accessory-1.jpeg",
        "name": "Vievie Necklace",
        "type": "Handmade",
        "price": 50,
        "discount": null
      }
    ],
    "body": [
      {
        "id": 1,
        "inStock": 10,
        "listedOn": "04/24/2024",
        "image": "images/body/body-1.jpeg",
        "name": "Body Oil",
        "type": "For all skin type",
        "price": 15,
        "discount": 14.99
      },
      {
        "id": 2,
        "inStock": 200,
        "listedOn": "12/04/2023",
        "image": "images/body/body-1.jpeg",
        "name": "Body Lotion",
        "type": "For all skin type",
        "price": 15,
        "discount": 13.49
      },
      {
        "id": 3,
        "inStock": 0,
        "listedOn": "01/12/2023",
        "image": "images/body/body-1.jpeg",
        "name": "Body Shower Gel",
        "type": "For all skin type",
        "price": 10,
        "discount": null
      },
      {
        "id": 4,
        "inStock": 10,
        "listedOn": "01/12/2023",
        "image": "images/body/body-1.jpeg",
        "name": "Body Moisturizer Spray",
        "type": "For sensitive skin",
        "price": 10,
        "discount": null
      },
      {
        "id": 5,
        "inStock": 1000,
        "listedOn": "01/12/2023",
        "image": "images/body/body-1.jpeg",
        "name": "Body Scrub",
        "type": "For normal skin",
        "price": 10,
        "discount": null
      }
    ],
    "face": [
      {
        "id": 1,
        "inStock": 10,
        "listedOn": "04/24/2024",
        "image": "images/face/face-1.jpeg",
        "name": "Soothing Cleanser",
        "type": "For oily skin type",
        "price": 15,
        "discount": 14.99
      },
      {
        "id": 2,
        "inStock": 10,
        "listedOn": "04/24/2023",
        "image": "images/face/face-1.jpeg",
        "name": "Face Mask",
        "type": "For all skin type",
        "price": 8.5,
        "discount": 8
      },
      {
        "id": 3,
        "inStock": 10,
        "listedOn": "04/24/2022",
        "image": "images/face/face-1.jpeg",
        "name": "Restore Gel",
        "type": "For all skin type",
        "price": 75,
        "discount": null
      },
      {
        "id": 4,
        "inStock": 50,
        "listedOn": "01/01/2024",
        "image": "images/face/face-1.jpeg",
        "name": "Mint Face Water",
        "type": "For dry skin type",
        "price": 85,
        "discount": null
      },
      {
        "id": 5,
        "inStock": 10,
        "listedOn": "04/24/2020",
        "image": "images/face/face-1.jpeg",
        "name": "Ultra Facial Cream",
        "type": "Mature skin care",
        "price": 150,
        "discount": 144.99
      }
    ],
    "hair": [
      {
        "id": 1,
        "inStock": 100,
        "listedOn": "08/01/2024",
        "image": "images/hair/hair-1.jpg",
        "name": "Avocado Shampoo",
        "type": "For dry hair skin",
        "price": 17.99,
        "discount": 15
      },
      {
        "id": 2,
        "inStock": 40,
        "listedOn": "07/1/2022",
        "image": "images/hair/hair-1.jpg",
        "name": "Hair dryer",
        "type": "For all hair type",
        "price": 45,
        "discount": null
      }
    ],
    "home_style": [
      {
        "id": 1,
        "inStock": 100,
        "listedOn": "05/01/2024",
        "image": "images/home-style/home-1.jpeg",
        "name": "Fragrance Spray",
        "type": "For rooms",
        "price": 15,
        "discount": 14.99
      },
      {
        "id": 2,
        "inStock": 0,
        "listedOn": "05/01/2021",
        "image": "images/home-style/home-1.jpeg",
        "name": "Pillow",
        "type": "For your bed",
        "price": 105,
        "discount": null
      }
    ]
  }
]
